{
	"pages": [ //pages数组中第一项表示应用启动页，参考：https://uniapp.dcloud.io/collocation/pages
		{
			"path": "pages/index/index",
			"style": {
				"navigationBarTitleText": "加减号"
			}
		},
		{
			"path": "pages/find/index",
			"style": {
				"navigationBarTitleText": "发现"
			}
		},
		{
			"path": "pages/message/index",
			"style": {
				"navigationBarTitleText": "消息"
			}
		},
		{
			"path": "pages/mine/index",
			"style": {
				"navigationBarTitleText": "我的"
			}
		},
		{
			"path": "pages/item/index",
			"style": {
				"navigationBarTitleText": "内容"
			}
		}
	],
	"globalStyle": {
		"navigationBarTextStyle": "black",
		"navigationBarTitleText": "uni-app",
		"navigationBarBackgroundColor": "#F8F8F8",
		"backgroundColor": "#F8F8F8"
	},
	"tabBar":{
		"color":"#333",
		"selectedColor":"#005bac",
		"list":[
			{
				"pagePath":"pages/index/index",
				"text":"首页",
				"iconPath":"static/icon/footer_1.png",
				"selectedIconPath":"static/icon/footer_1_red.png"
			},
			{
				"pagePath":"pages/find/index",
				"text":"发现",
				"iconPath":"static/icon/footer_2.png",
				"selectedIconPath":"static/icon/footer_2_red.png"
			},
			{
				"pagePath":"pages/message/index",
				"text":"消息",
				"iconPath":"static/icon/footer_3.png",
				"selectedIconPath":"static/icon/footer_3_red.png"
			},
			{
				"pagePath":"pages/mine/index",
				"text":"我的",
				"iconPath":"static/icon/footer_4.png",
				"selectedIconPath":"static/icon/footer_4_red.png"
			}
		]
	}
}
